{
  "flight_number": "UY417",
  "date": "2026-02-26",
  "scheduled_departure_unix": 1772109840,
  "status": "scheduled",
  "pnrs": [
    {
      "pnr": "XH33ZB",
      "policyId": 590537,
      "policyholder": "NA",
      "wallet": "IJ4EOFWUKA3MKJVJ2FUPTLW2QWHLY2PYVZOBKQC5QRRNC7DLN7KIFFJGKE",
      "passenger": {
        "name": "Micah Ramirez",
        "fullName": "Micah Ramirez",
        "email": "micah.ramirez34@yahoo.com",
        "phone": "+1-479-527-2406",
        "phone_number": "+1-479-527-2406",
        "date_of_birth": "1976-11-06",
        "dateOfBirth": "1976-11-06",
        "passport_number": "PXH33ZB199",
        "documentId": "PXH33ZB199",
        "address": null,
        "seat": "10A",
        "class": null,
        "classType": null
      },
      "nft_metadata_url": "https://is.gd/BO5DgT",
      "created_at": 1771590553,
      "updated_at": 1771590553
    },
    {
      "pnr": "VT9Z3L",
      "policyId": "NA",
      "policyholder": "NA",
      "wallet": "NA",
      "passenger": {
        "fullName": "Zoe Hernandez",
        "dateOfBirth": "1972-05-15",
        "documentId": "PVT9Z3L540",
        "seat": "12F",
        "email": "zoe.hernandez50@gmail.com",
        "phone": "+1-256-529-6803"
      },
      "nft_metadata_url": "NA",
      "created_at": 1771525776,
      "updated_at": 1771525776
    },
    {
      "pnr": "GHDT7E",
      "policyId": "NA",
      "policyholder": "NA",
      "wallet": "NA",
      "passenger": {
        "fullName": "Kai Morales",
        "dateOfBirth": "1955-01-25",
        "documentId": "PGHDT7E380",
        "seat": "15D",
        "email": "kai.morales41@yahoo.com",
        "phone": "+1-741-871-7945"
      },
      "nft_metadata_url": "NA",
      "created_at": 1771525776,
      "updated_at": 1771525776
    }
  ],
  "created_at": 1771525776,
  "updated_at": 1771590553
}